MANIFEST.in
README.txt
setup.cfg
setup.py
docs/HISTORY.txt
horae/__init__.py
horae.auth.egg-info/PKG-INFO
horae.auth.egg-info/SOURCES.txt
horae.auth.egg-info/dependency_links.txt
horae.auth.egg-info/entry_points.txt
horae.auth.egg-info/namespace_packages.txt
horae.auth.egg-info/not-zip-safe
horae.auth.egg-info/requires.txt
horae.auth.egg-info/top_level.txt
horae/auth/__init__.py
horae/auth/auth.py
horae/auth/configure.zcml
horae/auth/events.py
horae/auth/interfaces.py
horae/auth/overrides.zcml
horae/auth/permissions.py
horae/auth/roles.py
horae/auth/securitypolicy.py
horae/auth/utils.py
horae/auth/viewlets.py
horae/auth/views.py
horae/auth/vocabulary.py
horae/auth/locales/horae.auth.pot
horae/auth/locales/de/LC_MESSAGES/horae.auth.mo
horae/auth/locales/de/LC_MESSAGES/horae.auth.po
horae/auth/templates/login.cpt
horae/auth/templates/logout.cpt
horae/auth/templates/sharing.cpt
horae/auth/viewlet_templates/loginlogout.cpt